pyoperaciones/__init__.py
pyoperaciones-0.1.dist-info/LICENSE.txt
pyoperaciones-0.1.dist-info/METADATA
pyoperaciones-0.1.dist-info/WHEEL
pyoperaciones-0.1.dist-info/top_level.txt
pyoperaciones-0.1.dist-info/RECORD
