Metadata-Version: 2.1
Name: pyoperaciones
Version: 0.1
Summary: A tool to perform mathematical operations with prime numbers.
Home-page: UNKNOWN
Author: Alvaro Millán
Author-email: amillanblas94@gmail.com
License: GNU GPLv3
Keywords: pyoperaciones mathematical operations with prime numbers
Platform: UNKNOWN
Classifier: Development Status :: 4 - Beta
Classifier: Intended Audience :: Developers
Classifier: Topic :: Utilities
Classifier: License :: OSI Approved :: GNU General Public License v3 (GPLv3)
Classifier: Programming Language :: Python :: 3
Classifier: Operating System :: OS Independent
